LICENSE
MANIFEST.in
README.rst
requirements.txt
setup.cfg
setup.py
Flask_PW3.1.egg-info/PKG-INFO
Flask_PW3.1.egg-info/SOURCES.txt
Flask_PW3.1.egg-info/dependency_links.txt
Flask_PW3.1.egg-info/requires.txt
Flask_PW3.1.egg-info/top_level.txt
flask_pw/__init__.py
flask_pw/debugtoolbar.py
flask_pw/models.py