Metadata-Version: 2.1
Name: Flask-PW3.1
Version: 0.0.3
Summary: Peewee ORM integration for Flask framework
Home-page: https://github.com/jianc65/flask-pw3
Author: Keigo Hattori
Author-email: keigoht@gmail.com
License: UNKNOWN
Keywords: flask,peewee,migrations,migrate,signals
Platform: Any
Classifier: Development Status :: 4 - Beta
Classifier: Intended Audience :: Developers
Classifier: License :: OSI Approved :: BSD License
Classifier: Natural Language :: English
Classifier: Operating System :: OS Independent
Classifier: Programming Language :: Python :: 2
Classifier: Programming Language :: Python :: 3
Classifier: Programming Language :: Python
Classifier: Topic :: Software Development :: Libraries :: Python Modules
Classifier: Topic :: Software Development :: Testing
Classifier: Topic :: Utilities
